setup.py
django_paypal_adaptive.egg-info/PKG-INFO
django_paypal_adaptive.egg-info/SOURCES.txt
django_paypal_adaptive.egg-info/dependency_links.txt
django_paypal_adaptive.egg-info/requires.txt
django_paypal_adaptive.egg-info/top_level.txt
paypaladaptive/__init__.py
paypaladaptive/admin.py
paypaladaptive/decorators.py
paypaladaptive/forms.py
paypaladaptive/models.py
paypaladaptive/settings.py
paypaladaptive/tasks.py
paypaladaptive/urls.py
paypaladaptive/views.py
paypaladaptive/api/__init__.py
paypaladaptive/api/datatypes.py
paypaladaptive/api/endpoints.py
paypaladaptive/api/errors.py
paypaladaptive/api/httpwrapper.py
paypaladaptive/api/ipn/__init__.py
paypaladaptive/api/ipn/constants.py
paypaladaptive/api/ipn/endpoints.py
paypaladaptive/tests/__init__.py
paypaladaptive/tests/factories.py
paypaladaptive/tests/helpers.py
paypaladaptive/tests/ipn.py
paypaladaptive/tests/mock_url_request.py
paypaladaptive/tests/payment.py
paypaladaptive/tests/payment_response.py
paypaladaptive/tests/payment_return_url.py
paypaladaptive/tests/payment_update.py
paypaladaptive/tests/preapproval_cancel.py
paypaladaptive/tests/preapproval_return_url.py
paypaladaptive/tests/preapproval_update.py
paypaladaptive/tests/tests.py