Metadata-Version: 1.1
Name: django-paypal-adaptive
Version: 0.2.1
Summary: A pluggable Django application for integrating PayPal Adaptive Payments
Home-page: http://github.com/FundedByMe/django-paypal-adaptive
Author: Anton Agestam
Author-email: msn@antonagestam.se
License: UNKNOWN
Platform: UNKNOWN
Classifier: Framework :: Django
Classifier: Intended Audience :: Developers
Classifier: Intended Audience :: System Administrators
Classifier: Operating System :: OS Independent
Classifier: Topic :: Software Development
